DESCRIPTION.rst
MANIFEST.in
NOTICE
README.rst
setup.cfg
setup.py
src/pytractor/__init__.py
src/pytractor/exceptions.py
src/pytractor/mixins.py
src/pytractor/webdriver.py
src/pytractor/protractor/extracted/allowAnimations.js
src/pytractor/protractor/extracted/evaluate.js
src/pytractor/protractor/extracted/findAllRepeaterRows.js
src/pytractor/protractor/extracted/findBindings.js
src/pytractor/protractor/extracted/findByButtonText.js
src/pytractor/protractor/extracted/findByCssContainingText.js
src/pytractor/protractor/extracted/findByModel.js
src/pytractor/protractor/extracted/findByOptions.js
src/pytractor/protractor/extracted/findByPartialButtonText.js
src/pytractor/protractor/extracted/findRepeaterColumn.js
src/pytractor/protractor/extracted/findRepeaterElement.js
src/pytractor/protractor/extracted/findRepeaterRows.js
src/pytractor/protractor/extracted/getLocationAbsUrl.js
src/pytractor/protractor/extracted/getPendingHttpRequests.js
src/pytractor/protractor/extracted/installInBrowser.js
src/pytractor/protractor/extracted/setLocation.js
src/pytractor/protractor/extracted/testForAngular.js
src/pytractor/protractor/extracted/waitForAngular.js
src/pytractor/tests/__init__.py
src/pytractor/tests/functional/__init__.py
src/pytractor/tests/functional/test_base.py
src/pytractor/tests/functional/test_helpers.py
src/pytractor/tests/functional/test_locators.py
src/pytractor/tests/functional/test_wait.py
src/pytractor/tests/functional/test_webdriver.py
src/pytractor/tests/functional/testdriver.py
src/pytractor/tests/functional/testserver.py
src/pytractor/tests/functional/testapp/LICENSE
src/pytractor/tests/functional/testapp/alt_root_index.html
src/pytractor/tests/functional/testapp/app.css
src/pytractor/tests/functional/testapp/app.js
src/pytractor/tests/functional/testapp/favicon.ico
src/pytractor/tests/functional/testapp/index-no-angular.html
src/pytractor/tests/functional/testapp/index.html
src/pytractor/tests/functional/testapp/login.html
src/pytractor_back.egg-info/PKG-INFO
src/pytractor_back.egg-info/SOURCES.txt
src/pytractor_back.egg-info/dependency_links.txt
src/pytractor_back.egg-info/requires.txt
src/pytractor_back.egg-info/top_level.txt