Metadata-Version: 1.1
Name: pytractor-back
Version: 0.2.2
Summary: Selenium testing for Angular.js apps. Adopted for Python 3.7.
Home-page: https://github.com/lexadler/pytractor-back
Author: Konrad Podloucky
Author-email: konrad+pytractor@crunchy-frog.org
License: Apache 2.0
Keywords: selenium angular.js testing
Platform: UNKNOWN
Classifier: Development Status :: 3 - Alpha
Classifier: Intended Audience :: Developers
Classifier: Topic :: Software Development :: Testing
Classifier: License :: OSI Approved :: Apache Software License
Classifier: Programming Language :: Python :: 3.7
